Metadata-Version: 2.1
Name: statspy-probability
Version: 0.1a0
Summary: Gaussian and Binomial distributions
Home-page: UNKNOWN
Author: Rodrigo Toledo
Author-email: rodrigo.pp.toledo@gmail.com
License: UNKNOWN
Platform: UNKNOWN
